lk_blingfire.cpython-313-darwin.so
livekit/blingfire/__init__.py
livekit/blingfire/py.typed
livekit/blingfire/version.py
livekit_blingfire-1.1.0.dist-info/METADATA
livekit_blingfire-1.1.0.dist-info/WHEEL
livekit_blingfire-1.1.0.dist-info/top_level.txt
livekit_blingfire-1.1.0.dist-info/RECORD
